super_image/__init__.py
super_image/__main__.py
super_image/cli.py
super_image/configuration_utils.py
super_image/file_utils.py
super_image/modeling_utils.py
super_image/trainer.py
super_image/trainer_drn.py
super_image/trainer_utils.py
super_image/training_args.py
super_image/data/__init__.py
super_image/data/builder.py
super_image/data/datasets.py
super_image/data/loader.py
super_image/data/metrics.py
super_image/models/__init__.py
super_image/models/a2n/configuration_a2n.py
super_image/models/a2n/modeling_a2n.py
super_image/models/awsrn/configuration_awsrn.py
super_image/models/awsrn/modeling_awsrn.py
super_image/models/carn/configuration_carn.py
super_image/models/carn/modeling_carn.py
super_image/models/ddbpn/configuration_ddbpn.py
super_image/models/ddbpn/modeling_ddbpn.py
super_image/models/drln/configuration_drln.py
super_image/models/drln/modeling_drln.py
super_image/models/drn/configuration_drn.py
super_image/models/drn/modeling_drn.py
super_image/models/edsr/configuration_edsr.py
super_image/models/edsr/modeling_edsr.py
super_image/models/han/configuration_han.py
super_image/models/han/modeling_han.py
super_image/models/jiif/configuration_jiif.py
super_image/models/jiif/modeling_jiif.py
super_image/models/liif/configuration_liif.py
super_image/models/liif/modeling_liif.py
super_image/models/masa/configuration_masa.py
super_image/models/masa/modeling_masa.py
super_image/models/mdsr/configuration_mdsr.py
super_image/models/mdsr/modeling_mdsr.py
super_image/models/msrn/configuration_msrn.py
super_image/models/msrn/modeling_msrn.py
super_image/models/pan/configuration_pan.py
super_image/models/pan/modeling_pan.py
super_image/models/physicssr/configuration_physicssr.py
super_image/models/physicssr/modeling_physicssr.py
super_image/models/rcan/configuration_rcan.py
super_image/models/rcan/modeling_rcan.py
super_image/models/rnan/configuration_rnan.py
super_image/models/rnan/modeling_rnan.py
super_image/models/smsr/configuration_smsr.py
super_image-0.2.0.dist-info/METADATA
super_image-0.2.0.dist-info/WHEEL
super_image-0.2.0.dist-info/entry_points.txt
super_image-0.2.0.dist-info/licenses/LICENSE
super_image-0.2.0.dist-info/RECORD
