Metadata-Version: 2.4
Name: super-image
Version: 0.2.0
Summary: State-of-the-art image super resolution models for PyTorch.
Project-URL: Homepage, https://github.com/eugenesiow/super-image
Project-URL: Repository, https://github.com/eugenesiow/super-image
Author-email: Eugene Siow <kyo116@gmail.com>
License: Apache License
License-File: LICENSE
Requires-Python: >=3.6.2
Requires-Dist: h5py>=3.1.0
Requires-Dist: huggingface-hub>=0.0.13
Requires-Dist: opencv-python>=4.5.2.54
Requires-Dist: torch>=1.9.0
Requires-Dist: torchvision>=0.10.0
Requires-Dist: tqdm>=4.61.2
